download_link_replacer/__init__.py
download_link_replacer/directives.py
download_link_replacer/events.py
download_link_replacer/utils.py
download_link_replacer-1.0.6.dist-info/licenses/LICENSE
download_link_replacer-1.0.6.dist-info/METADATA
download_link_replacer-1.0.6.dist-info/WHEEL
download_link_replacer-1.0.6.dist-info/top_level.txt
download_link_replacer-1.0.6.dist-info/RECORD
