Metadata-Version: 2.4
Name: download_link_replacer
Version: 1.0.6
Summary: A tool to replace download links in sphinx books, JupyterBooks v1 and TeachBooks.
Author-email: rstular <r.stular@student.tudelft.nl>
Requires-Python: >=3.9
License-File: LICENSE
Requires-Dist: sphinx
Requires-Dist: importlib
Dynamic: license-file
